{
    "dataset": "unfiltered",
    "output_dir": "baseline",
    "word_embed": "bert",
    "encoder": "gru",
    "pooling": "avg",
    "bidirectional": true,
    "save_best_model": true,
    "viz_projection": true,
    "class_weight": "inverse",
    "loss": "focal",
    "n_heads": 1,
    "n_layers": 2,
    "n_epochs": 15,
    "batch_size": 8,
    "exclude_cls_before": false,
    "exclude_cls_after": false,
    "freeze_embedding": false,
    "normalize_logits": false,
    "device": "cuda",
    "scenario_dir": "experiments/baseline_15/unfiltered/gru/inverse/focal/avg/2/1/bidirectional",
    "best_epoch": 8,
    "best_val_f1": 0.9581913489786797,
    "best_val_acc": 0.9575892857142857,
    "train_started_at": "2024-02-03 04:07:55.978000",
    "train_finished_at": "2024-02-03 04:10:28.471190",
    "train_duration": "152.49319 seconds",
    "eval_started_at": "2024-02-03 04:10:28.857751",
    "eval_finished_at": "2024-02-03 04:10:29.528963",
    "eval_duration": "0.671212 seconds"
}