{
    "dataset": "unfiltered",
    "output_dir": "baseline",
    "word_embed": "bert",
    "encoder": "transformer",
    "pooling": "avg",
    "bidirectional": false,
    "save_best_model": true,
    "viz_projection": true,
    "class_weight": "balanced",
    "loss": "cross_entropy",
    "n_heads": 6,
    "n_layers": 3,
    "n_epochs": 15,
    "batch_size": 8,
    "exclude_cls_before": false,
    "exclude_cls_after": false,
    "freeze_embedding": false,
    "normalize_logits": false,
    "device": "cuda",
    "scenario_dir": "experiments/baseline_15/unfiltered/transformer/balanced/cross_entropy/avg/3/6/unidirectional",
    "best_epoch": 13,
    "best_val_f1": 0.9561091384633212,
    "best_val_acc": 0.9553571428571429,
    "train_started_at": "2024-02-03 07:37:12.551055",
    "train_finished_at": "2024-02-03 07:39:45.662133",
    "train_duration": "153.111078 seconds",
    "eval_started_at": "2024-02-03 07:39:46.002751",
    "eval_finished_at": "2024-02-03 07:39:46.628070",
    "eval_duration": "0.625319 seconds"
}