{
    "dataset": "unfiltered",
    "output_dir": "multitask",
    "word_embed": "bert",
    "encoder": "lstm",
    "pooling": "max",
    "bidirectional": true,
    "save_best_model": false,
    "viz_projection": true,
    "class_weight": "inverse",
    "loss": "logloss",
    "n_heads": 1,
    "n_layers": 2,
    "n_epochs": 15,
    "batch_size": 8,
    "exclude_cls_before": false,
    "exclude_cls_after": false,
    "freeze_embedding": false,
    "normalize_logits": false,
    "device": "cuda",
    "scenario_dir": "experiments/multitask_15/unfiltered/lstm/inverse/logloss/max/2/1/bidirectional",
    "best_epoch": 12,
    "best_val_acc": 0.9553571428571429,
    "best_val_f1": 0.9576537868749772,
    "train_started_at": "2024-02-06 00:13:56.727879",
    "train_finished_at": "2024-02-06 00:16:32.430887",
    "train_duration": "155.703008 seconds",
    "eval_started_at": "2024-02-06 00:16:32.754773",
    "eval_finished_at": "2024-02-06 00:16:33.606737",
    "eval_duration": "0.851964 seconds"
}