{
    "dataset": "unfiltered",
    "output_dir": "baseline",
    "word_embed": "bert",
    "encoder": "lstm",
    "pooling": "avg",
    "bidirectional": false,
    "save_best_model": true,
    "viz_projection": true,
    "class_weight": "inverse",
    "loss": "focal",
    "n_heads": 1,
    "n_layers": 1,
    "n_epochs": 15,
    "batch_size": 8,
    "exclude_cls_before": false,
    "exclude_cls_after": false,
    "freeze_embedding": false,
    "normalize_logits": false,
    "device": "cuda",
    "scenario_dir": "experiments/baseline_15/unfiltered/lstm/inverse/focal/avg/1/1/unidirectional",
    "best_epoch": 3,
    "best_val_f1": 0.9576173222105189,
    "best_val_acc": 0.9553571428571429,
    "train_started_at": "2024-02-04 08:19:50.113920",
    "train_finished_at": "2024-02-04 08:22:17.285974",
    "train_duration": "147.172054 seconds",
    "eval_started_at": "2024-02-04 08:22:17.678434",
    "eval_finished_at": "2024-02-04 08:22:18.460155",
    "eval_duration": "0.781721 seconds"
}