{
    "dataset": "unfiltered",
    "output_dir": "baseline",
    "word_embed": "bert",
    "encoder": "gru",
    "pooling": "avg",
    "bidirectional": false,
    "save_best_model": true,
    "viz_projection": true,
    "class_weight": "uniform",
    "loss": "cross_entropy",
    "n_heads": 1,
    "n_layers": 1,
    "n_epochs": 15,
    "batch_size": 8,
    "exclude_cls_before": false,
    "exclude_cls_after": false,
    "freeze_embedding": false,
    "normalize_logits": false,
    "device": "cuda",
    "scenario_dir": "experiments/baseline_15/unfiltered/gru/uniform/cross_entropy/avg/1/1/unidirectional",
    "best_epoch": 2,
    "best_val_f1": 0.954384513791634,
    "best_val_acc": 0.9553571428571429,
    "train_started_at": "2024-02-04 08:36:57.281194",
    "train_finished_at": "2024-02-04 08:39:22.659228",
    "train_duration": "145.378034 seconds",
    "eval_started_at": "2024-02-04 08:39:23.057425",
    "eval_finished_at": "2024-02-04 08:39:23.770472",
    "eval_duration": "0.713047 seconds"
}