{
    "dataset": "unfiltered",
    "output_dir": "baseline",
    "word_embed": "bert",
    "encoder": "gru",
    "pooling": "avg",
    "bidirectional": false,
    "save_best_model": true,
    "viz_projection": true,
    "class_weight": "uniform",
    "loss": "cross_entropy",
    "n_heads": 1,
    "n_layers": 1,
    "n_epochs": 15,
    "batch_size": 8,
    "exclude_cls_before": false,
    "exclude_cls_after": false,
    "freeze_embedding": false,
    "normalize_logits": false,
    "device": "cuda",
    "scenario_dir": "experiments/baseline_15/unfiltered/gru/uniform/cross_entropy/avg/1/1/unidirectional",
    "best_epoch": 12,
    "best_val_f1": 0.9553365118408722,
    "best_val_acc": 0.9553571428571429,
    "train_started_at": "2024-02-03 02:42:56.458687",
    "train_finished_at": "2024-02-03 02:45:21.477201",
    "train_duration": "145.018514 seconds",
    "eval_started_at": "2024-02-03 02:45:21.804071",
    "eval_finished_at": "2024-02-03 02:45:22.445937",
    "eval_duration": "0.641866 seconds"
}