{
    "dataset": "unfiltered",
    "output_dir": "multitask",
    "word_embed": "bert",
    "encoder": "gru",
    "pooling": "last",
    "bidirectional": false,
    "save_best_model": false,
    "viz_projection": true,
    "class_weight": "uniform",
    "loss": "logloss",
    "n_heads": 1,
    "n_layers": 1,
    "n_epochs": 15,
    "batch_size": 8,
    "exclude_cls_before": false,
    "exclude_cls_after": false,
    "freeze_embedding": false,
    "normalize_logits": false,
    "device": "cuda",
    "scenario_dir": "experiments/multitask_15/unfiltered/gru/uniform/logloss/last/1/1/unidirectional",
    "best_epoch": 5,
    "best_val_acc": 0.9486607142857143,
    "best_val_f1": 0.948588607831663,
    "train_started_at": "2024-02-06 02:41:12.443082",
    "train_finished_at": "2024-02-06 02:43:38.281125",
    "train_duration": "145.838043 seconds",
    "eval_started_at": "2024-02-06 02:43:38.616180",
    "eval_finished_at": "2024-02-06 02:43:39.429512",
    "eval_duration": "0.813332 seconds"
}