{
    "dataset": "unfiltered",
    "output_dir": "baseline",
    "word_embed": "bert",
    "encoder": "lstm",
    "pooling": "avg",
    "bidirectional": false,
    "save_best_model": true,
    "viz_projection": true,
    "class_weight": "inverse",
    "loss": "focal",
    "n_heads": 1,
    "n_layers": 3,
    "n_epochs": 15,
    "batch_size": 8,
    "exclude_cls_before": false,
    "exclude_cls_after": false,
    "freeze_embedding": false,
    "normalize_logits": false,
    "device": "cuda",
    "scenario_dir": "experiments/baseline_15/unfiltered/lstm/inverse/focal/avg/3/1/unidirectional",
    "best_epoch": 10,
    "best_val_f1": 0.9543714116770107,
    "best_val_acc": 0.9508928571428571,
    "train_started_at": "2024-02-03 02:37:18.428986",
    "train_finished_at": "2024-02-03 02:40:16.173438",
    "train_duration": "177.744452 seconds",
    "eval_started_at": "2024-02-03 02:40:16.599285",
    "eval_finished_at": "2024-02-03 02:40:17.346191",
    "eval_duration": "0.746906 seconds"
}