{
    "dataset": "filtered",
    "output_dir": "baseline",
    "word_embed": "bert",
    "encoder": "lstm",
    "pooling": "max",
    "bidirectional": false,
    "save_best_model": true,
    "viz_projection": true,
    "class_weight": "uniform",
    "loss": "cross_entropy",
    "n_heads": 1,
    "n_layers": 2,
    "n_epochs": 15,
    "batch_size": 8,
    "exclude_cls_before": false,
    "exclude_cls_after": false,
    "freeze_embedding": false,
    "normalize_logits": false,
    "device": "cuda",
    "scenario_dir": "experiments/baseline_15/filtered/lstm/uniform/cross_entropy/max/2/1/unidirectional",
    "best_epoch": 14,
    "best_val_f1": 0.7902863729074556,
    "best_val_acc": 0.7948717948717948,
    "train_started_at": "2024-02-04 20:15:18.787419",
    "train_finished_at": "2024-02-04 20:16:02.840084",
    "train_duration": "44.052665 seconds",
    "eval_started_at": "2024-02-04 20:16:03.170616",
    "eval_finished_at": "2024-02-04 20:16:03.484522",
    "eval_duration": "0.313906 seconds"
}