{
    "dataset": "unfiltered",
    "output_dir": "baseline",
    "word_embed": "bert",
    "encoder": "gru",
    "pooling": "avg",
    "bidirectional": false,
    "save_best_model": true,
    "viz_projection": true,
    "class_weight": "inverse",
    "loss": "focal",
    "n_heads": 1,
    "n_layers": 2,
    "n_epochs": 15,
    "batch_size": 8,
    "exclude_cls_before": false,
    "exclude_cls_after": false,
    "freeze_embedding": false,
    "normalize_logits": false,
    "device": "cuda",
    "scenario_dir": "experiments/baseline_15/unfiltered/gru/inverse/focal/avg/2/1/unidirectional",
    "best_epoch": 15,
    "best_val_f1": 0.9508018099302861,
    "best_val_acc": 0.9508928571428571,
    "train_started_at": "2024-02-03 04:10:37.786241",
    "train_finished_at": "2024-02-03 04:13:18.172703",
    "train_duration": "160.386462 seconds",
    "eval_started_at": "2024-02-03 04:13:18.552948",
    "eval_finished_at": "2024-02-03 04:13:19.233896",
    "eval_duration": "0.680948 seconds"
}