{
    "dataset": "filtered",
    "output_dir": "exclude_cls",
    "word_embed": "bert",
    "encoder": "lstm",
    "pooling": "last",
    "bidirectional": false,
    "save_best_model": false,
    "viz_projection": true,
    "class_weight": "inverse",
    "loss": "logloss",
    "n_heads": 1,
    "n_layers": 2,
    "n_epochs": 15,
    "batch_size": 8,
    "exclude_cls_before": true,
    "exclude_cls_after": false,
    "freeze_embedding": false,
    "normalize_logits": false,
    "device": "cuda",
    "scenario_dir": "experiments/exclude_cls_15/filtered/lstm/inverse/logloss/last/2/1/unidirectional",
    "best_epoch": 11,
    "best_val_acc": 0.7863247863247863,
    "best_val_f1": 0.7820612390938417,
    "train_started_at": "2024-02-20 03:20:34.608123",
    "train_finished_at": "2024-02-20 03:21:17.529832",
    "train_duration": "42.921709 seconds",
    "eval_started_at": "2024-02-20 03:21:17.895668",
    "eval_finished_at": "2024-02-20 03:21:18.209290",
    "eval_duration": "0.313622 seconds"
}